soil_heat/__init__.py
soil_heat/gao_et_al.py
soil_heat/liebethal_and_folken.py
soil_heat/soil_heat.py
soil_heat/wang_and_bouzeid.py
soil_heat/wang_and_yang.py
soil_heat-0.1.1.dist-info/licenses/AUTHORS.rst
soil_heat-0.1.1.dist-info/licenses/LICENSE
soil_heat-0.1.1.dist-info/METADATA
soil_heat-0.1.1.dist-info/WHEEL
soil_heat-0.1.1.dist-info/top_level.txt
soil_heat-0.1.1.dist-info/RECORD
